PyQtVisa/QVisaApplication.py
PyQtVisa/QVisaConfigure.py
PyQtVisa/__init__.py
PyQtVisa/drivers/QVisaDevice.py
PyQtVisa/drivers/__init__.py
PyQtVisa/drivers/keithley2400.py
PyQtVisa/utils/QVisaColorMap.py
PyQtVisa/utils/QVisaDataObject.py
PyQtVisa/utils/__init__.py
PyQtVisa/widgets/QVisaDeviceControl.py
PyQtVisa/widgets/QVisaDeviceSelect.py
PyQtVisa/widgets/QVisaDynamicPlot.py
PyQtVisa/widgets/QVisaMetaWidget.py
PyQtVisa/widgets/QVisaResourceList.py
PyQtVisa/widgets/QVisaSaveWidget.py
PyQtVisa/widgets/QVisaUnitSelector.py
PyQtVisa/widgets/__init__.py
PyQtVisa-1.1.dev6.dist-info/LICENSE
PyQtVisa-1.1.dev6.dist-info/METADATA
PyQtVisa-1.1.dev6.dist-info/WHEEL
PyQtVisa-1.1.dev6.dist-info/top_level.txt
PyQtVisa-1.1.dev6.dist-info/RECORD
